[
  {
    "date": "2024-03-15",
    "open": 160.7,
    "high": 160.3033,
    "low": 161.38,
    "close": null,
    "volume": 10956888
  },
  {
    "date": "2024-03-18",
    "open": 161.48,
    "high": 161,
    "low": 161.21,
    "close": null,
    "volume": 6086268
  },
  {
    "date": "2024-03-19",
    "open": 161.8,
    "high": 161.17,
    "low": 161.83,
    "close": null,
    "volume": 6148240
  },
  {
    "date": "2024-03-20",
    "open": 162.01,
    "high": 161.47,
    "low": 161.99,
    "close": null,
    "volume": 4870296
  },
  {
    "date": "2024-03-21",
    "open": 162.09,
    "high": 161.115,
    "low": 161.86,
    "close": null,
    "volume": 5211676
  },
  {
    "date": "2024-03-22",
    "open": 162.2,
    "high": 161.47,
    "low": 161.66,
    "close": null,
    "volume": 6393425
  },
  {
    "date": "2024-03-25",
    "open": 161.17,
    "high": 159.73,
    "low": 160.19,
    "close": null,
    "volume": 7145692
  },
  {
    "date": "2024-03-26",
    "open": 160.36,
    "high": 160.14,
    "low": 160.55,
    "close": null,
    "volume": 5842850
  },
  {
    "date": "2024-03-27",
    "open": 161.36,
    "high": 161.34,
    "low": 162.61,
    "close": null,
    "volume": 6599711
  },
  {
    "date": "2024-03-28",
    "open": 162.82,
    "high": 161.7,
    "low": 162.25,
    "close": null,
    "volume": 7191571
  },
  {
    "date": "2024-04-01",
    "open": 161.78,
    "high": 159.8,
    "low": 160.58,
    "close": null,
    "volume": 5971857
  },
  {
    "date": "2024-04-02",
    "open": 159.64,
    "high": 159.64,
    "low": 160.57,
    "close": null,
    "volume": 6771395
  },
  {
    "date": "2024-04-03",
    "open": 160.63,
    "high": 155.68,
    "low": 156.15,
    "close": null,
    "volume": 9601812
  },
  {
    "date": "2024-04-04",
    "open": 156.88,
    "high": 155.41,
    "low": 155.45,
    "close": null,
    "volume": 6801662
  },
  {
    "date": "2024-04-05",
    "open": 155.29,
    "high": 154.69,
    "low": 156.1,
    "close": null,
    "volume": 5121197
  },
  {
    "date": "2024-04-08",
    "open": 155.97,
    "high": 155.63,
    "low": 156.04,
    "close": null,
    "volume": 5476752
  },
  {
    "date": "2024-04-09",
    "open": 156.27,
    "high": 155.7,
    "low": 156.66,
    "close": null,
    "volume": 4613751
  },
  {
    "date": "2024-04-10",
    "open": 155.65,
    "high": 155.65,
    "low": 157.24,
    "close": null,
    "volume": 7785084
  },
  {
    "date": "2024-04-11",
    "open": 157.55,
    "high": 155.77,
    "low": 155.84,
    "close": null,
    "volume": 8209765
  },
  {
    "date": "2024-04-12",
    "open": 155.22,
    "high": 154.74,
    "low": 155.33,
    "close": null,
    "volume": 6770659
  },
  {
    "date": "2024-04-15",
    "open": 156.42,
    "high": 155.33,
    "low": 155.45,
    "close": null,
    "volume": 5753987
  },
  {
    "date": "2024-04-16",
    "open": 155.85,
    "high": 155.665,
    "low": 155.95,
    "close": null,
    "volume": 6103296
  },
  {
    "date": "2024-04-17",
    "open": 156.3,
    "high": 155.74,
    "low": 156.96,
    "close": null,
    "volume": 6621906
  },
  {
    "date": "2024-04-18",
    "open": 156.34,
    "high": 155.96,
    "low": 157.29,
    "close": null,
    "volume": 7819261
  },
  {
    "date": "2024-04-19",
    "open": 154.98,
    "high": 153.53,
    "low": 158.14,
    "close": null,
    "volume": 12028400
  },
  {
    "date": "2024-04-22",
    "open": 158.43,
    "high": 157.2525,
    "low": 160.54,
    "close": null,
    "volume": 8926327
  },
  {
    "date": "2024-04-23",
    "open": 161.68,
    "high": 160.415,
    "low": 161.5,
    "close": null,
    "volume": 7707250
  },
  {
    "date": "2024-04-24",
    "open": 161.2,
    "high": 159.42,
    "low": 162.6,
    "close": null,
    "volume": 7217563
  },
  {
    "date": "2024-04-25",
    "open": 162.97,
    "high": 162.08,
    "low": 162.55,
    "close": null,
    "volume": 7094620
  },
  {
    "date": "2024-04-26",
    "open": 162.5,
    "high": 160.49,
    "low": 161.29,
    "close": null,
    "volume": 5659784
  },
  {
    "date": "2024-04-29",
    "open": 161.17,
    "high": 160.41,
    "low": 161.66,
    "close": null,
    "volume": 4622164
  },
  {
    "date": "2024-04-30",
    "open": 161.84,
    "high": 161.6,
    "low": 163.2,
    "close": null,
    "volume": 8106098
  },
  {
    "date": "2024-05-01",
    "open": 163.28,
    "high": 162.22,
    "low": 163.4,
    "close": null,
    "volume": 7543154
  },
  {
    "date": "2024-05-02",
    "open": 163.54,
    "high": 162.6401,
    "low": 163.84,
    "close": null,
    "volume": 5647490
  },
  {
    "date": "2024-05-03",
    "open": 163.54,
    "high": 162.16,
    "low": 164.46,
    "close": null,
    "volume": 5581692
  },
  {
    "date": "2024-05-06",
    "open": 164.78,
    "high": 163.2629,
    "low": 164.44,
    "close": null,
    "volume": 5472549
  },
  {
    "date": "2024-05-07",
    "open": 164.98,
    "high": 164.59,
    "low": 165.76,
    "close": null,
    "volume": 6433090
  },
  {
    "date": "2024-05-08",
    "open": 165.98,
    "high": 164.93,
    "low": 165.07,
    "close": null,
    "volume": 4579471
  },
  {
    "date": "2024-05-09",
    "open": 165.05,
    "high": 165.05,
    "low": 166.04,
    "close": null,
    "volume": 4671126
  },
  {
    "date": "2024-05-10",
    "open": 166.09,
    "high": 165.7,
    "low": 166.85,
    "close": null,
    "volume": 4879427
  },
  {
    "date": "2024-05-13",
    "open": 166.85,
    "high": 165.36,
    "low": 165.87,
    "close": null,
    "volume": 5725523
  },
  {
    "date": "2024-05-14",
    "open": 165.53,
    "high": 163.95,
    "low": 165.76,
    "close": null,
    "volume": 6009837
  },
  {
    "date": "2024-05-15",
    "open": 165.31,
    "high": 165.12,
    "low": 166.51,
    "close": null,
    "volume": 5102897
  },
  {
    "date": "2024-05-16",
    "open": 166.93,
    "high": 166.59,
    "low": 167.86,
    "close": null,
    "volume": 6793672
  },
  {
    "date": "2024-05-17",
    "open": 167.67,
    "high": 166.88,
    "low": 167.64,
    "close": null,
    "volume": 4700819
  },
  {
    "date": "2024-05-20",
    "open": 167.55,
    "high": 166.7905,
    "low": 167.31,
    "close": null,
    "volume": 3804823
  },
  {
    "date": "2024-05-21",
    "open": 167.76,
    "high": 167.2902,
    "low": 168.35,
    "close": null,
    "volume": 5147065
  },
  {
    "date": "2024-05-22",
    "open": 168.01,
    "high": 167.6268,
    "low": 167.81,
    "close": null,
    "volume": 4536733
  },
  {
    "date": "2024-05-23",
    "open": 167.29,
    "high": 165.32,
    "low": 165.49,
    "close": null,
    "volume": 4729792
  },
  {
    "date": "2024-05-24",
    "open": 165.85,
    "high": 165.15,
    "low": 165.33,
    "close": null,
    "volume": 3820090
  },
  {
    "date": "2024-05-28",
    "open": 164.49,
    "high": 162.26,
    "low": 163.11,
    "close": null,
    "volume": 6466193
  },
  {
    "date": "2024-05-29",
    "open": 162.65,
    "high": 161.42,
    "low": 161.65,
    "close": null,
    "volume": 4360383
  },
  {
    "date": "2024-05-30",
    "open": 161.65,
    "high": 161.48,
    "low": 162.58,
    "close": null,
    "volume": 4756454
  },
  {
    "date": "2024-05-31",
    "open": 162.44,
    "high": 161.97,
    "low": 164.54,
    "close": null,
    "volume": 10341644
  },
  {
    "date": "2024-06-03",
    "open": 163.93,
    "high": 163.63,
    "low": 164.65,
    "close": null,
    "volume": 5828442
  },
  {
    "date": "2024-06-04",
    "open": 164.79,
    "high": 164.4,
    "low": 167.01,
    "close": null,
    "volume": 6277001
  },
  {
    "date": "2024-06-05",
    "open": 167.01,
    "high": 164.98,
    "low": 166.05,
    "close": null,
    "volume": 5243345
  },
  {
    "date": "2024-06-06",
    "open": 165.83,
    "high": 165.08,
    "low": 168.47,
    "close": null,
    "volume": 6302243
  },
  {
    "date": "2024-06-07",
    "open": 168.4,
    "high": 166.84,
    "low": 167.06,
    "close": null,
    "volume": 4558190
  },
  {
    "date": "2024-06-10",
    "open": 166.78,
    "high": 166.08,
    "low": 167.35,
    "close": null,
    "volume": 4110668
  },
  {
    "date": "2024-06-11",
    "open": 166.97,
    "high": 166.02,
    "low": 167.48,
    "close": null,
    "volume": 3947671
  },
  {
    "date": "2024-06-12",
    "open": 167.5,
    "high": 164.2209,
    "low": 165.18,
    "close": null,
    "volume": 5474498
  },
  {
    "date": "2024-06-13",
    "open": 164.47,
    "high": 164.47,
    "low": 166.41,
    "close": null,
    "volume": 4902180
  },
  {
    "date": "2024-06-14",
    "open": 165.99,
    "high": 165.25,
    "low": 166.79,
    "close": null,
    "volume": 3694974
  },
  {
    "date": "2024-06-17",
    "open": 165.85,
    "high": 165.4,
    "low": 167.5,
    "close": null,
    "volume": 6759352
  },
  {
    "date": "2024-06-18",
    "open": 167.03,
    "high": 166.94,
    "low": 168.56,
    "close": null,
    "volume": 5112634
  },
  {
    "date": "2024-06-20",
    "open": 168.37,
    "high": 166.86,
    "low": 167.67,
    "close": null,
    "volume": 8483606
  },
  {
    "date": "2024-06-21",
    "open": 167.48,
    "high": 167.18,
    "low": 168.26,
    "close": null,
    "volume": 14682061
  },
  {
    "date": "2024-06-24",
    "open": 168.76,
    "high": 167.48,
    "low": 168.45,
    "close": null,
    "volume": 7565304
  },
  {
    "date": "2024-06-25",
    "open": 168.63,
    "high": 165.9,
    "low": 166.85,
    "close": null,
    "volume": 8323968
  },
  {
    "date": "2024-06-26",
    "open": 166.05,
    "high": 165.66,
    "low": 167.45,
    "close": null,
    "volume": 5164046
  },
  {
    "date": "2024-06-27",
    "open": 167.49,
    "high": 165.5,
    "low": 166.62,
    "close": null,
    "volume": 5006990
  },
  {
    "date": "2024-06-28",
    "open": 166,
    "high": 164.58,
    "low": 164.92,
    "close": null,
    "volume": 9253317
  },
  {
    "date": "2024-07-01",
    "open": 165.59,
    "high": 162.2,
    "low": 162.72,
    "close": null,
    "volume": 7638639
  },
  {
    "date": "2024-07-02",
    "open": 162.58,
    "high": 161.71,
    "low": 163.9,
    "close": null,
    "volume": 5449219
  },
  {
    "date": "2024-07-03",
    "open": 163.21,
    "high": 162.975,
    "low": 163.83,
    "close": null,
    "volume": 2980461
  },
  {
    "date": "2024-07-05",
    "open": 164.01,
    "high": 163.5,
    "low": 165.21,
    "close": null,
    "volume": 6509248
  },
  {
    "date": "2024-07-08",
    "open": 165.95,
    "high": 165.62,
    "low": 166.52,
    "close": null,
    "volume": 5144458
  },
  {
    "date": "2024-07-09",
    "open": 166.63,
    "high": 165.14,
    "low": 165.66,
    "close": null,
    "volume": 4393179
  },
  {
    "date": "2024-07-10",
    "open": 165.9,
    "high": 165.54,
    "low": 166.8,
    "close": null,
    "volume": 5037097
  },
  {
    "date": "2024-07-11",
    "open": 166.3,
    "high": 164.78,
    "low": 165.54,
    "close": null,
    "volume": 5833061
  },
  {
    "date": "2024-07-12",
    "open": 166.22,
    "high": 166.02,
    "low": 166.61,
    "close": null,
    "volume": 4684642
  },
  {
    "date": "2024-07-15",
    "open": 166.49,
    "high": 164.46,
    "low": 164.58,
    "close": null,
    "volume": 5752513
  },
  {
    "date": "2024-07-16",
    "open": 164.91,
    "high": 164.61,
    "low": 166.95,
    "close": null,
    "volume": 6378312
  },
  {
    "date": "2024-07-17",
    "open": 167.75,
    "high": 167.33,
    "low": 169.44,
    "close": null,
    "volume": 7982328
  },
  {
    "date": "2024-07-18",
    "open": 168.8,
    "high": 168.28,
    "low": 168.44,
    "close": null,
    "volume": 5926346
  },
  {
    "date": "2024-07-19",
    "open": 167.97,
    "high": 167.13,
    "low": 167.96,
    "close": null,
    "volume": 6597090
  },
  {
    "date": "2024-07-22",
    "open": 167.93,
    "high": 167.7,
    "low": 168.25,
    "close": null,
    "volume": 6383031
  },
  {
    "date": "2024-07-23",
    "open": 168.11,
    "high": 166.32,
    "low": 166.62,
    "close": null,
    "volume": 4863398
  },
  {
    "date": "2024-07-24",
    "open": 166.32,
    "high": 165.575,
    "low": 168,
    "close": null,
    "volume": 5906992
  },
  {
    "date": "2024-07-25",
    "open": 168.32,
    "high": 166.87,
    "low": 166.9,
    "close": null,
    "volume": 7338521
  },
  {
    "date": "2024-07-26",
    "open": 167.25,
    "high": 167.03,
    "low": 169.11,
    "close": null,
    "volume": 5581557
  },
  {
    "date": "2024-07-29",
    "open": 168.85,
    "high": 168.11,
    "low": 169.93,
    "close": null,
    "volume": 6797832
  },
  {
    "date": "2024-07-30",
    "open": 161.79,
    "high": 158.04,
    "low": 161.7,
    "close": null,
    "volume": 15746254
  },
  {
    "date": "2024-07-31",
    "open": 160.81,
    "high": 159.21,
    "low": 160.76,
    "close": null,
    "volume": 9660902
  },
  {
    "date": "2024-08-01",
    "open": 160.88,
    "high": 160.68,
    "low": 165.69,
    "close": null,
    "volume": 12532700
  },
  {
    "date": "2024-08-02",
    "open": 167.44,
    "high": 165.15,
    "low": 170.08,
    "close": null,
    "volume": 11899038
  },
  {
    "date": "2024-08-05",
    "open": 170.88,
    "high": 166.67,
    "low": 168.06,
    "close": null,
    "volume": 10338767
  },
  {
    "date": "2024-08-06",
    "open": 167.9,
    "high": 167.85,
    "low": 168.09,
    "close": null,
    "volume": 7454869
  },
  {
    "date": "2024-08-07",
    "open": 168.57,
    "high": 168.01,
    "low": 170.02,
    "close": null,
    "volume": 8385546
  },
  {
    "date": "2024-08-08",
    "open": 169.42,
    "high": 169,
    "low": 170.87,
    "close": null,
    "volume": 6386941
  },
  {
    "date": "2024-08-09",
    "open": 170.12,
    "high": 169.65,
    "low": 170.54,
    "close": null,
    "volume": 5377378
  },
  {
    "date": "2024-08-12",
    "open": 169.4,
    "high": 166.2,
    "low": 166.81,
    "close": null,
    "volume": 7208103
  },
  {
    "date": "2024-08-13",
    "open": 167.34,
    "high": 166.46,
    "low": 167.29,
    "close": null,
    "volume": 3770007
  },
  {
    "date": "2024-08-14",
    "open": 166.5,
    "high": 165.82,
    "low": 168.8,
    "close": null,
    "volume": 5476675
  },
  {
    "date": "2024-08-15",
    "open": 169.46,
    "high": 166.75,
    "low": 167.92,
    "close": null,
    "volume": 9491625
  },
  {
    "date": "2024-08-16",
    "open": 167.82,
    "high": 166.8,
    "low": 167.89,
    "close": null,
    "volume": 5640925
  },
  {
    "date": "2024-08-19",
    "open": 168.18,
    "high": 168.17,
    "low": 168.42,
    "close": null,
    "volume": 3885315
  },
  {
    "date": "2024-08-20",
    "open": 168.77,
    "high": 168.11,
    "low": 170.41,
    "close": null,
    "volume": 4513600
  },
  {
    "date": "2024-08-21",
    "open": 170.19,
    "high": 169.6,
    "low": 170.16,
    "close": null,
    "volume": 4082026
  },
  {
    "date": "2024-08-22",
    "open": 170.88,
    "high": 169.14,
    "low": 170.15,
    "close": null,
    "volume": 4097382
  },
  {
    "date": "2024-08-23",
    "open": 170.05,
    "high": 168.25,
    "low": 169.17,
    "close": null,
    "volume": 4771267
  },
  {
    "date": "2024-08-26",
    "open": 168.695,
    "high": 168.695,
    "low": 170.35,
    "close": null,
    "volume": 6472417
  },
  {
    "date": "2024-08-27",
    "open": 170.83,
    "high": 169.08,
    "low": 169.25,
    "close": null,
    "volume": 4456635
  },
  {
    "date": "2024-08-28",
    "open": 169.42,
    "high": 168.58,
    "low": 169.06,
    "close": null,
    "volume": 5645040
  },
  {
    "date": "2024-08-29",
    "open": 169.75,
    "high": 168.94,
    "low": 170.03,
    "close": null,
    "volume": 4413165
  },
  {
    "date": "2024-08-30",
    "open": 170.16,
    "high": 169.69,
    "low": 171.54,
    "close": null,
    "volume": 7301617
  },
  {
    "date": "2024-09-03",
    "open": 171.03,
    "high": 170.99,
    "low": 174.52,
    "close": null,
    "volume": 10101418
  },
  {
    "date": "2024-09-04",
    "open": 173.63,
    "high": 173.63,
    "low": 175.9,
    "close": null,
    "volume": 7517526
  },
  {
    "date": "2024-09-05",
    "open": 175.99,
    "high": 174.67,
    "low": 175.47,
    "close": null,
    "volume": 6061865
  },
  {
    "date": "2024-09-06",
    "open": 175.76,
    "high": 175.34,
    "low": 175.59,
    "close": null,
    "volume": 5785684
  },
  {
    "date": "2024-09-09",
    "open": 175.54,
    "high": 174.66,
    "low": 176.06,
    "close": null,
    "volume": 6450204
  },
  {
    "date": "2024-09-10",
    "open": 175.91,
    "high": 175.91,
    "low": 177.79,
    "close": null,
    "volume": 6396311
  },
  {
    "date": "2024-09-11",
    "open": 176.6,
    "high": 173.63,
    "low": 173.92,
    "close": null,
    "volume": 6828173
  },
  {
    "date": "2024-09-12",
    "open": 173.9,
    "high": 172.44,
    "low": 173.47,
    "close": null,
    "volume": 4839752
  },
  {
    "date": "2024-09-13",
    "open": 173.37,
    "high": 172.8,
    "low": 174.08,
    "close": null,
    "volume": 3917986
  },
  {
    "date": "2024-09-16",
    "open": 174.71,
    "high": 174.32,
    "low": 177.24,
    "close": null,
    "volume": 6892335
  },
  {
    "date": "2024-09-17",
    "open": 176.625,
    "high": 175.36,
    "low": 175.88,
    "close": null,
    "volume": 4757247
  },
  {
    "date": "2024-09-18",
    "open": 175.05,
    "high": 172.57,
    "low": 173.92,
    "close": null,
    "volume": 5102884
  },
  {
    "date": "2024-09-19",
    "open": 172.88,
    "high": 170.38,
    "low": 171.54,
    "close": null,
    "volume": 8692016
  },
  {
    "date": "2024-09-20",
    "open": 171.51,
    "high": 171.5,
    "low": 174.22,
    "close": null,
    "volume": 28647462
  },
  {
    "date": "2024-09-23",
    "open": 174.01,
    "high": 172.5901,
    "low": 173.77,
    "close": null,
    "volume": 10265199
  },
  {
    "date": "2024-09-24",
    "open": 172.88,
    "high": 172.615,
    "low": 173.24,
    "close": null,
    "volume": 5422351
  },
  {
    "date": "2024-09-25",
    "open": 174.07,
    "high": 172.06,
    "low": 172.26,
    "close": null,
    "volume": 8916483
  },
  {
    "date": "2024-09-26",
    "open": 171.5,
    "high": 171.36,
    "low": 173.21,
    "close": null,
    "volume": 4957367
  },
  {
    "date": "2024-09-27",
    "open": 173.01,
    "high": 172.58,
    "low": 173.55,
    "close": null,
    "volume": 4599709
  },
  {
    "date": "2024-09-30",
    "open": 173.73,
    "high": 172.71,
    "low": 173.2,
    "close": null,
    "volume": 6296653
  },
  {
    "date": "2024-10-01",
    "open": 173.24,
    "high": 172.2,
    "low": 173.04,
    "close": null,
    "volume": 7130825
  },
  {
    "date": "2024-10-02",
    "open": 172.01,
    "high": 171.08,
    "low": 171.92,
    "close": null,
    "volume": 6212890
  },
  {
    "date": "2024-10-03",
    "open": 171.37,
    "high": 169.77,
    "low": 170.12,
    "close": null,
    "volume": 4794348
  },
  {
    "date": "2024-10-04",
    "open": 168.85,
    "high": 168.26,
    "low": 168.88,
    "close": null,
    "volume": 6003668
  },
  {
    "date": "2024-10-07",
    "open": 169.16,
    "high": 166.87,
    "low": 167.12,
    "close": null,
    "volume": 6325281
  },
  {
    "date": "2024-10-08",
    "open": 166.85,
    "high": 166.27,
    "low": 168.16,
    "close": null,
    "volume": 7472965
  },
  {
    "date": "2024-10-09",
    "open": 168.38,
    "high": 168,
    "low": 169.27,
    "close": null,
    "volume": 8758806
  },
  {
    "date": "2024-10-10",
    "open": 168.8,
    "high": 168.37,
    "low": 168.95,
    "close": null,
    "volume": 6932308
  },
  {
    "date": "2024-10-11",
    "open": 169.46,
    "high": 168.97,
    "low": 171.09,
    "close": null,
    "volume": 7036480
  },
  {
    "date": "2024-10-14",
    "open": 171.02,
    "high": 170.74,
    "low": 172.51,
    "close": null,
    "volume": 5909158
  },
  {
    "date": "2024-10-15",
    "open": 172.89,
    "high": 172.815,
    "low": 173.57,
    "close": null,
    "volume": 7172262
  },
  {
    "date": "2024-10-16",
    "open": 171.88,
    "high": 170.89,
    "low": 172.38,
    "close": null,
    "volume": 6117053
  },
  {
    "date": "2024-10-17",
    "open": 172.18,
    "high": 171.76,
    "low": 172.28,
    "close": null,
    "volume": 7045586
  },
  {
    "date": "2024-10-18",
    "open": 170.3,
    "high": 168.46,
    "low": 171.28,
    "close": null,
    "volume": 8372536
  },
  {
    "date": "2024-10-21",
    "open": 170.975,
    "high": 168.45,
    "low": 169.54,
    "close": null,
    "volume": 5522460
  },
  {
    "date": "2024-10-22",
    "open": 168.57,
    "high": 168.57,
    "low": 169.7,
    "close": null,
    "volume": 7511671
  },
  {
    "date": "2024-10-23",
    "open": 169.55,
    "high": 168.725,
    "low": 169.58,
    "close": null,
    "volume": 4837810
  },
  {
    "date": "2024-10-24",
    "open": 169.42,
    "high": 168.93,
    "low": 169.62,
    "close": null,
    "volume": 5861303
  },
  {
    "date": "2024-10-25",
    "open": 168.92,
    "high": 168.041,
    "low": 168.22,
    "close": null,
    "volume": 4877911
  },
  {
    "date": "2024-10-28",
    "open": 169.28,
    "high": 168.375,
    "low": 169.3,
    "close": null,
    "volume": 5754043
  },
  {
    "date": "2024-10-29",
    "open": 168.86,
    "high": 166.83,
    "low": 167.17,
    "close": null,
    "volume": 5681358
  },
  {
    "date": "2024-10-30",
    "open": 167.09,
    "high": 165.96,
    "low": 166.16,
    "close": null,
    "volume": 5518085
  },
  {
    "date": "2024-10-31",
    "open": 165.76,
    "high": 165.09,
    "low": 165.18,
    "close": null,
    "volume": 6056514
  },
  {
    "date": "2024-11-01",
    "open": 165.31,
    "high": 164.985,
    "low": 165.1,
    "close": null,
    "volume": 5455095
  },
  {
    "date": "2024-11-04",
    "open": 165.72,
    "high": 164.58,
    "low": 165.08,
    "close": null,
    "volume": 5130338
  },
  {
    "date": "2024-11-05",
    "open": 164.33,
    "high": 164.33,
    "low": 165.76,
    "close": null,
    "volume": 4397441
  },
  {
    "date": "2024-11-06",
    "open": 165.61,
    "high": 159.81,
    "low": 161.05,
    "close": null,
    "volume": 11473688
  },
  {
    "date": "2024-11-07",
    "open": 161.96,
    "high": 161.475,
    "low": 163.41,
    "close": null,
    "volume": 9056725
  },
  {
    "date": "2024-11-08",
    "open": 164.015,
    "high": 163.93,
    "low": 167.71,
    "close": null,
    "volume": 7506566
  },
  {
    "date": "2024-11-11",
    "open": 167,
    "high": 165.775,
    "low": 166.03,
    "close": null,
    "volume": 6364403
  },
  {
    "date": "2024-11-12",
    "open": 166.14,
    "high": 165.57,
    "low": 165.84,
    "close": null,
    "volume": 6507823
  },
  {
    "date": "2024-11-13",
    "open": 166.06,
    "high": 165.68,
    "low": 166.58,
    "close": null,
    "volume": 5412566
  },
  {
    "date": "2024-11-14",
    "open": 166.65,
    "high": 166.51,
    "low": 167.08,
    "close": null,
    "volume": 7444273
  },
  {
    "date": "2024-11-15",
    "open": 167.86,
    "high": 166.88,
    "low": 169.54,
    "close": null,
    "volume": 9939416
  },
  {
    "date": "2024-11-18",
    "open": 169.11,
    "high": 168.8301,
    "low": 170.75,
    "close": null,
    "volume": 6681087
  },
  {
    "date": "2024-11-19",
    "open": 170.69,
    "high": 169.66,
    "low": 170.76,
    "close": null,
    "volume": 5683673
  },
  {
    "date": "2024-11-20",
    "open": 170.01,
    "high": 169.50549,
    "low": 170.89,
    "close": null,
    "volume": 7081237
  },
  {
    "date": "2024-11-21",
    "open": 171.66,
    "high": 170.22,
    "low": 172.75,
    "close": null,
    "volume": 6240403
  },
  {
    "date": "2024-11-22",
    "open": 174.145,
    "high": 173.88,
    "low": 176.28,
    "close": null,
    "volume": 10609785
  },
  {
    "date": "2024-11-25",
    "open": 177.48,
    "high": 176.904,
    "low": 177.39,
    "close": null,
    "volume": 19357005
  },
  {
    "date": "2024-11-26",
    "open": 177.2,
    "high": 177.2,
    "low": 179.31,
    "close": null,
    "volume": 6276933
  },
  {
    "date": "2024-11-27",
    "open": 179.96,
    "high": 178.725,
    "low": 179.36,
    "close": null,
    "volume": 5522912
  },
  {
    "date": "2024-11-29",
    "open": 178.7,
    "high": 178.28,
    "low": 179.26,
    "close": null,
    "volume": 3823708
  },
  {
    "date": "2024-12-02",
    "open": 179.12,
    "high": 178.01,
    "low": 179.7,
    "close": null,
    "volume": 5728297
  },
  {
    "date": "2024-12-03",
    "open": 179.4282,
    "high": 175.2,
    "low": 175.42,
    "close": null,
    "volume": 8127329
  },
  {
    "date": "2024-12-04",
    "open": 174.17,
    "high": 173.46,
    "low": 175.11,
    "close": null,
    "volume": 6823659
  },
  {
    "date": "2024-12-05",
    "open": 174.86,
    "high": 174.45,
    "low": 176.03,
    "close": null,
    "volume": 5022189
  },
  {
    "date": "2024-12-06",
    "open": 175.37,
    "high": 173.75,
    "low": 173.82,
    "close": null,
    "volume": 5741167
  },
  {
    "date": "2024-12-09",
    "open": 173.635,
    "high": 170.43,
    "low": 170.79,
    "close": null,
    "volume": 7164286
  },
  {
    "date": "2024-12-10",
    "open": 170.42,
    "high": 169.93,
    "low": 172.28,
    "close": null,
    "volume": 6220088
  },
  {
    "date": "2024-12-11",
    "open": 173.01,
    "high": 170.395,
    "low": 170.63,
    "close": null,
    "volume": 5237533
  },
  {
    "date": "2024-12-12",
    "open": 171.43,
    "high": 170.02,
    "low": 170.85,
    "close": null,
    "volume": 4072810
  },
  {
    "date": "2024-12-13",
    "open": 170.77,
    "high": 170.12,
    "low": 171.06,
    "close": null,
    "volume": 3884513
  },
  {
    "date": "2024-12-16",
    "open": 171.445,
    "high": 171.0975,
    "low": 171.14,
    "close": null,
    "volume": 5943680
  },
  {
    "date": "2024-12-17",
    "open": 170.67,
    "high": 170.02,
    "low": 170.33,
    "close": null,
    "volume": 6069344
  },
  {
    "date": "2024-12-18",
    "open": 169.76,
    "high": 169.02,
    "low": 169.08,
    "close": null,
    "volume": 7517081
  },
  {
    "date": "2024-12-19",
    "open": 169.01,
    "high": 167.35,
    "low": 169.19,
    "close": null,
    "volume": 8585220
  },
  {
    "date": "2024-12-20",
    "open": 168.87,
    "high": 167.5,
    "low": 168.06,
    "close": null,
    "volume": 21999342
  },
  {
    "date": "2024-12-23",
    "open": 168.06,
    "high": 166.36,
    "low": 168.11,
    "close": null,
    "volume": 6984079
  },
  {
    "date": "2024-12-24",
    "open": 167.63,
    "high": 167.42,
    "low": 168.94,
    "close": null,
    "volume": 2460756
  },
  {
    "date": "2024-12-26",
    "open": 168.595,
    "high": 168.07,
    "low": 170.16,
    "close": null,
    "volume": 3629533
  },
  {
    "date": "2024-12-27",
    "open": 169.42,
    "high": 169.26,
    "low": 169.53,
    "close": null,
    "volume": 4367879
  },
  {
    "date": "2024-12-30",
    "open": 168.665,
    "high": 166.71,
    "low": 167.09,
    "close": null,
    "volume": 4354543
  },
  {
    "date": "2024-12-31",
    "open": 167.36,
    "high": 166.59,
    "low": 167.65,
    "close": null,
    "volume": 3957920
  },
  {
    "date": "2025-01-02",
    "open": 168.085,
    "high": 165.91,
    "low": 165.98,
    "close": null,
    "volume": 5401712
  },
  {
    "date": "2025-01-03",
    "open": 166.25,
    "high": 164.25,
    "low": 165.13,
    "close": null,
    "volume": 5256807
  },
  {
    "date": "2025-01-06",
    "open": 162.81,
    "high": 160.44,
    "low": 160.6,
    "close": null,
    "volume": 8731671
  },
  {
    "date": "2025-01-07",
    "open": 161.46,
    "high": 160.74,
    "low": 161.3,
    "close": null,
    "volume": 8447744
  },
  {
    "date": "2025-01-08",
    "open": 160.99,
    "high": 160.565,
    "low": 162.1,
    "close": null,
    "volume": 4974783
  },
  {
    "date": "2025-01-10",
    "open": 160.3,
    "high": 157.47,
    "low": 158.56,
    "close": null,
    "volume": 8501525
  },
  {
    "date": "2025-01-13",
    "open": 159.35,
    "high": 158.41,
    "low": 158.84,
    "close": null,
    "volume": 6772198
  },
  {
    "date": "2025-01-14",
    "open": 158.85,
    "high": 158.31,
    "low": 159.74,
    "close": null,
    "volume": 5982254
  },
  {
    "date": "2025-01-15",
    "open": 160.59,
    "high": 159.335,
    "low": 159.65,
    "close": null,
    "volume": 8059231
  },
  {
    "date": "2025-01-16",
    "open": 159.62,
    "high": 159.135,
    "low": 160.5,
    "close": null,
    "volume": 5774429
  },
  {
    "date": "2025-01-17",
    "open": 159.74,
    "high": 159.6,
    "low": 161.13,
    "close": null,
    "volume": 7262739
  },
  {
    "date": "2025-01-21",
    "open": 161.42,
    "high": 160.96,
    "low": 161.72,
    "close": null,
    "volume": 13914694
  },
  {
    "date": "2025-01-22",
    "open": 167.1,
    "high": 164.44,
    "low": 164.74,
    "close": null,
    "volume": 14356691
  },
  {
    "date": "2025-01-23",
    "open": 163.88,
    "high": 163.32,
    "low": 166.15,
    "close": null,
    "volume": 7614308
  },
  {
    "date": "2025-01-24",
    "open": 165.91,
    "high": 163.2,
    "low": 164.12,
    "close": null,
    "volume": 6199939
  },
  {
    "date": "2025-01-27",
    "open": 166.72,
    "high": 166.11,
    "low": 169.66,
    "close": null,
    "volume": 9170829
  },
  {
    "date": "2025-01-28",
    "open": 168.91,
    "high": 166.11,
    "low": 166.19,
    "close": null,
    "volume": 6716387
  },
  {
    "date": "2025-01-29",
    "open": 166.705,
    "high": 165.8805,
    "low": 166.23,
    "close": null,
    "volume": 4850295
  },
  {
    "date": "2025-01-30",
    "open": 167.48,
    "high": 165.93,
    "low": 167.41,
    "close": null,
    "volume": 4136546
  },
  {
    "date": "2025-01-31",
    "open": 166,
    "high": 165.21,
    "low": 165.99,
    "close": null,
    "volume": 5464903
  },
  {
    "date": "2025-02-03",
    "open": 165.47,
    "high": 165.23,
    "low": 168.76,
    "close": null,
    "volume": 8668729
  },
  {
    "date": "2025-02-04",
    "open": 169.29,
    "high": 166.28,
    "low": 168.13,
    "close": null,
    "volume": 6410938
  },
  {
    "date": "2025-02-05",
    "open": 168.09,
    "high": 166.61,
    "low": 169.01,
    "close": null,
    "volume": 7537232
  },
  {
    "date": "2025-02-06",
    "open": 169.37,
    "high": 168.03,
    "low": 168.88,
    "close": null,
    "volume": 4957889
  },
  {
    "date": "2025-02-07",
    "open": 169.09,
    "high": 167.87,
    "low": 167.97,
    "close": null,
    "volume": 4535617
  },
  {
    "date": "2025-02-10",
    "open": 167.69,
    "high": 166.4,
    "low": 167.53,
    "close": null,
    "volume": 7063167
  },
  {
    "date": "2025-02-11",
    "open": 167.69,
    "high": 166.5,
    "low": 169.43,
    "close": null,
    "volume": 5438081
  },
  {
    "date": "2025-02-12",
    "open": 168.35,
    "high": 167.97,
    "low": 169.58,
    "close": null,
    "volume": 6037671
  },
  {
    "date": "2025-02-13",
    "open": 169.63,
    "high": 169.14,
    "low": 171.02,
    "close": null,
    "volume": 6328365
  },
  {
    "date": "2025-02-14",
    "open": 169.79,
    "high": 162.3,
    "low": 162.89,
    "close": null,
    "volume": 13179478
  },
  {
    "date": "2025-02-18",
    "open": 163.35,
    "high": 162.2,
    "low": 165.43,
    "close": null,
    "volume": 7075681
  },
  {
    "date": "2025-02-19",
    "open": 166.1,
    "high": 165.24,
    "low": 166.49,
    "close": null,
    "volume": 7910823
  },
  {
    "date": "2025-02-20",
    "open": 163.15,
    "high": 162.8,
    "low": 167.21,
    "close": null,
    "volume": 6162601
  },
  {
    "date": "2025-02-21",
    "open": 167.44,
    "high": 165.92,
    "low": 170.23,
    "close": null,
    "volume": 9813720
  },
  {
    "date": "2025-02-24",
    "open": 170.22,
    "high": 169.79,
    "low": 170.54,
    "close": null,
    "volume": 8564057
  },
  {
    "date": "2025-02-25",
    "open": 171.28,
    "high": 170.8,
    "low": 172.65,
    "close": null,
    "volume": 7314856
  },
  {
    "date": "2025-02-26",
    "open": 172.28,
    "high": 170.65,
    "low": 171.3,
    "close": null,
    "volume": 5519041
  },
  {
    "date": "2025-02-27",
    "open": 170.85,
    "high": 170.63,
    "low": 171.97,
    "close": null,
    "volume": 5466965
  },
  {
    "date": "2025-02-28",
    "open": 173.58,
    "high": 171.85,
    "low": 173.84,
    "close": null,
    "volume": 10240069
  },
  {
    "date": "2025-03-03",
    "open": 173.58,
    "high": 173.51,
    "low": 175.59,
    "close": null,
    "volume": 7615570
  },
  {
    "date": "2025-03-04",
    "open": 176.75,
    "high": 172.91,
    "low": 173.18,
    "close": null,
    "volume": 12118023
  },
  {
    "date": "2025-03-05",
    "open": 173.38,
    "high": 173.02,
    "low": 174.61,
    "close": null,
    "volume": 6989086
  },
  {
    "date": "2025-03-06",
    "open": 175,
    "high": 172.8439,
    "low": 174.66,
    "close": null,
    "volume": 6702490
  },
  {
    "date": "2025-03-07",
    "open": 174.09,
    "high": 174.05,
    "low": 175.95,
    "close": null,
    "volume": 9566763
  },
  {
    "date": "2025-03-10",
    "open": 176.755,
    "high": 175.83,
    "low": 176.26,
    "close": null,
    "volume": 11047022
  },
  {
    "date": "2025-03-11",
    "open": 175.825,
    "high": 172.32,
    "low": 173.12,
    "close": null,
    "volume": 11032285
  },
  {
    "date": "2025-03-12",
    "open": 169.7,
    "high": 167.77,
    "low": 168.37,
    "close": null,
    "volume": 10159136
  },
  {
    "date": "2025-03-13",
    "open": 167.7,
    "high": 167.2779,
    "low": 168.59,
    "close": null,
    "volume": 6609126
  },
  {
    "date": "2025-03-14",
    "open": 167.79,
    "high": 166.62,
    "low": 167.97,
    "close": null,
    "volume": 6790624
  },
  {
    "date": "2025-03-17",
    "open": 168.37,
    "high": 168.13,
    "low": 169.76,
    "close": null,
    "volume": 9931678
  },
  {
    "date": "2025-03-18",
    "open": 170.07,
    "high": 167.58,
    "low": 167.71,
    "close": null,
    "volume": 6100242
  },
  {
    "date": "2025-03-19",
    "open": 167.87,
    "high": 167.11,
    "low": 168.57,
    "close": null,
    "volume": 7569165
  },
  {
    "date": "2025-03-20",
    "open": 169.16,
    "high": 166.03,
    "low": 167.55,
    "close": null,
    "volume": 8789167
  },
  {
    "date": "2025-03-21",
    "open": 167.14,
    "high": 164.12,
    "low": 166.69,
    "close": null,
    "volume": 16027251
  },
  {
    "date": "2025-03-24",
    "open": 166.43,
    "high": 165.36,
    "low": 165.65,
    "close": null,
    "volume": 6102109
  },
  {
    "date": "2025-03-25",
    "open": 165.3,
    "high": 162.195,
    "low": 162.85,
    "close": null,
    "volume": 8366736
  },
  {
    "date": "2025-03-26",
    "open": 163.35,
    "high": 162.99,
    "low": 166.58,
    "close": null,
    "volume": 7757259
  },
  {
    "date": "2025-03-27",
    "open": 167.87,
    "high": 166.62,
    "low": 168.71,
    "close": null,
    "volume": 6211735
  },
  {
    "date": "2025-03-28",
    "open": 169.38,
    "high": 167.62,
    "low": 168.03,
    "close": null,
    "volume": 5479306
  },
  {
    "date": "2025-03-31",
    "open": 168.1015,
    "high": 168.1015,
    "low": 170.42,
    "close": null,
    "volume": 11520451
  },
  {
    "date": "2025-04-01",
    "open": 170.57,
    "high": 169.06,
    "low": 170.56,
    "close": null,
    "volume": 7021507
  },
  {
    "date": "2025-04-02",
    "open": 170.07,
    "high": 168.31,
    "low": 169.5,
    "close": null,
    "volume": 6274548
  },
  {
    "date": "2025-04-03",
    "open": 174.23,
    "high": 170.73,
    "low": 172.39,
    "close": null,
    "volume": 9393270
  },
  {
    "date": "2025-04-04",
    "open": 171.765,
    "high": 163.47,
    "low": 163.75,
    "close": null,
    "volume": 13454205
  },
  {
    "date": "2025-04-07",
    "open": 163.66,
    "high": 159.19,
    "low": 160.23,
    "close": null,
    "volume": 15708009
  },
  {
    "date": "2025-04-08",
    "open": 162.31,
    "high": 156.71,
    "low": 158.39,
    "close": null,
    "volume": 11541114
  },
  {
    "date": "2025-04-09",
    "open": 157.36,
    "high": 156.69,
    "low": 162.32,
    "close": null,
    "volume": 10670212
  },
  {
    "date": "2025-04-10",
    "open": 162.9,
    "high": 160.75,
    "low": 163.56,
    "close": null,
    "volume": 10581571
  },
  {
    "date": "2025-04-11",
    "open": 163.37,
    "high": 162.62,
    "low": 166.91,
    "close": null,
    "volume": 8603200
  },
  {
    "date": "2025-04-14",
    "open": 167.04,
    "high": 165.78,
    "low": 169.13,
    "close": null,
    "volume": 9877411
  },
  {
    "date": "2025-04-15",
    "open": 169.365,
    "high": 168.28,
    "low": 168.47,
    "close": null,
    "volume": 8764978
  },
  {
    "date": "2025-04-16",
    "open": 169.285,
    "high": 165.79,
    "low": 166.39,
    "close": null,
    "volume": 5897634
  },
  {
    "date": "2025-04-17",
    "open": 167.53,
    "high": 167.35,
    "low": 170.63,
    "close": null,
    "volume": 7227061
  },
  {
    "date": "2025-04-21",
    "open": 169.89,
    "high": 164.28,
    "low": 165.75,
    "close": null,
    "volume": 8062360
  },
  {
    "date": "2025-04-22",
    "open": 165.92,
    "high": 164.535,
    "low": 167.88,
    "close": null,
    "volume": 7907421
  },
  {
    "date": "2025-04-23",
    "open": 166.4,
    "high": 163.11,
    "low": 165.73,
    "close": null,
    "volume": 9309164
  },
  {
    "date": "2025-04-24",
    "open": 160.5,
    "high": 156.58,
    "low": 159.53,
    "close": null,
    "volume": 20077665
  },
  {
    "date": "2025-04-25",
    "open": 159.88,
    "high": 157.77,
    "low": 161.02,
    "close": null,
    "volume": 12893200
  },
  {
    "date": "2025-04-28",
    "open": 161.04,
    "high": 160.39,
    "low": 161.85,
    "close": null,
    "volume": 8126981
  },
  {
    "date": "2025-04-29",
    "open": 161.285,
    "high": 159.2,
    "low": 162.26,
    "close": null,
    "volume": 8266154
  },
  {
    "date": "2025-04-30",
    "open": 162.45,
    "high": 159.95,
    "low": 162.57,
    "close": null,
    "volume": 12475539
  },
  {
    "date": "2025-05-01",
    "open": 160.655,
    "high": 159.05,
    "low": 159.98,
    "close": null,
    "volume": 6792815
  },
  {
    "date": "2025-05-02",
    "open": 160.925,
    "high": 159.9,
    "low": 160.52,
    "close": null,
    "volume": 5750165
  },
  {
    "date": "2025-05-05",
    "open": 160.89,
    "high": 158.02,
    "low": 158.83,
    "close": null,
    "volume": 7576219
  },
  {
    "date": "2025-05-06",
    "open": 158.04,
    "high": 157.6459,
    "low": 159.25,
    "close": null,
    "volume": 7703843
  },
  {
    "date": "2025-05-07",
    "open": 159.02,
    "high": 158.54,
    "low": 159.29,
    "close": null,
    "volume": 6430156
  },
  {
    "date": "2025-05-08",
    "open": 158.395,
    "high": 158.01,
    "low": 158.65,
    "close": null,
    "volume": 7230806
  },
  {
    "date": "2025-05-09",
    "open": 158.02,
    "high": 157.41,
    "low": 157.66,
    "close": null,
    "volume": 6453232
  },
  {
    "date": "2025-05-12",
    "open": 157.425,
    "high": 156.69,
    "low": 160.9,
    "close": null,
    "volume": 7378380
  },
  {
    "date": "2025-05-13",
    "open": 160.02,
    "high": 157.36,
    "low": 158.73,
    "close": null,
    "volume": 7780827
  },
  {
    "date": "2025-05-14",
    "open": 158.12,
    "high": 157.57,
    "low": 158.02,
    "close": null,
    "volume": 5988905
  },
  {
    "date": "2025-05-15",
    "open": 159.55,
    "high": 158.7,
    "low": 162.41,
    "close": null,
    "volume": 8727316
  },
  {
    "date": "2025-05-16",
    "open": 162.65,
    "high": 161.85,
    "low": 163.28,
    "close": null,
    "volume": 7100784
  },
  {
    "date": "2025-05-19",
    "open": 163.47,
    "high": 163.41,
    "low": 164.77,
    "close": null,
    "volume": 8120219
  },
  {
    "date": "2025-05-20",
    "open": 164.61,
    "high": 164.6,
    "low": 165.64,
    "close": null,
    "volume": 5576561
  },
  {
    "date": "2025-05-21",
    "open": 164.82,
    "high": 164.62,
    "low": 165.43,
    "close": null,
    "volume": 6424153
  },
  {
    "date": "2025-05-22",
    "open": 164.44,
    "high": 164.02,
    "low": 165.03,
    "close": null,
    "volume": 6245571
  },
  {
    "date": "2025-05-23",
    "open": 164.825,
    "high": 163.48,
    "low": 165.86,
    "close": null,
    "volume": 5349868
  },
  {
    "date": "2025-05-27",
    "open": 165.27,
    "high": 165.27,
    "low": 167.76,
    "close": null,
    "volume": 11423794
  },
  {
    "date": "2025-05-28",
    "open": 167.65,
    "high": 167.06,
    "low": 167.36,
    "close": null,
    "volume": 5385942
  },
  {
    "date": "2025-05-29",
    "open": 166.74,
    "high": 166.44,
    "low": 168.56,
    "close": null,
    "volume": 4842554
  },
  {
    "date": "2025-05-30",
    "open": 168.75,
    "high": 168.6,
    "low": 169.89,
    "close": null,
    "volume": 12587537
  },
  {
    "date": "2025-06-02",
    "open": 169.02,
    "high": 166.23,
    "low": 167.78,
    "close": null,
    "volume": 7574428
  },
  {
    "date": "2025-06-03",
    "open": 166.8,
    "high": 165.9,
    "low": 166.85,
    "close": null,
    "volume": 6223447
  },
  {
    "date": "2025-06-04",
    "open": 166.69,
    "high": 165.923,
    "low": 165.95,
    "close": null,
    "volume": 4939333
  },
  {
    "date": "2025-06-05",
    "open": 165.43,
    "high": 162.51,
    "low": 162.8,
    "close": null,
    "volume": 10352288
  },
  {
    "date": "2025-06-06",
    "open": 163.29,
    "high": 163.28,
    "low": 164.02,
    "close": null,
    "volume": 5697877
  },
  {
    "date": "2025-06-09",
    "open": 163.39,
    "high": 162.07,
    "low": 162.56,
    "close": null,
    "volume": 6544199
  },
  {
    "date": "2025-06-10",
    "open": 162.69,
    "high": 161.92,
    "low": 162.84,
    "close": null,
    "volume": 7680015
  },
  {
    "date": "2025-06-11",
    "open": 162.63,
    "high": 161.69,
    "low": 162.11,
    "close": null,
    "volume": 5960052
  },
  {
    "date": "2025-06-12",
    "open": 161.97,
    "high": 161.675,
    "low": 163.18,
    "close": null,
    "volume": 6509891
  },
  {
    "date": "2025-06-13",
    "open": 162.765,
    "high": 159.91,
    "low": 160.28,
    "close": null,
    "volume": 7104547
  },
  {
    "date": "2025-06-16",
    "open": 160.88,
    "high": 160.01,
    "low": 160.88,
    "close": null,
    "volume": 6331961
  },
  {
    "date": "2025-06-17",
    "open": 160.06,
    "high": 158.31,
    "low": 158.52,
    "close": null,
    "volume": 6809747
  },
  {
    "date": "2025-06-18",
    "open": 158.55,
    "high": 157.66,
    "low": 158.02,
    "close": null,
    "volume": 7211225
  },
  {
    "date": "2025-06-20",
    "open": 158.03,
    "high": 157.85,
    "low": 159.08,
    "close": null,
    "volume": 16173371
  },
  {
    "date": "2025-06-23",
    "open": 159.07,
    "high": 159,
    "low": 161.03,
    "close": null,
    "volume": 6588223
  },
  {
    "date": "2025-06-24",
    "open": 161.175,
    "high": 159.65,
    "low": 160.36,
    "close": null,
    "volume": 7470052
  },
  {
    "date": "2025-06-25",
    "open": 159.825,
    "high": 158.71,
    "low": 158.97,
    "close": null,
    "volume": 5933715
  },
  {
    "date": "2025-06-26",
    "open": 159.55,
    "high": 157.17,
    "low": 158.63,
    "close": null,
    "volume": 7410446
  },
  {
    "date": "2025-06-27",
    "open": 158.68,
    "high": 158.29,
    "low": 159.86,
    "close": null,
    "volume": 19256955
  },
  {
    "date": "2025-06-30",
    "open": 159.26,
    "high": 158.13,
    "low": 159.32,
    "close": null,
    "volume": 11238201
  },
  {
    "date": "2025-07-01",
    "open": 159.88,
    "high": 159.38,
    "low": 161.22,
    "close": null,
    "volume": 10664891
  },
  {
    "date": "2025-07-02",
    "open": 161.135,
    "high": 159.86,
    "low": 161.2,
    "close": null,
    "volume": 8848744
  },
  {
    "date": "2025-07-03",
    "open": 161.79,
    "high": 159.785,
    "low": 160.83,
    "close": null,
    "volume": 6999589
  },
  {
    "date": "2025-07-07",
    "open": 160.85,
    "high": 159.29,
    "low": 160.5,
    "close": null,
    "volume": 7225695
  },
  {
    "date": "2025-07-08",
    "open": 159.52,
    "high": 157.44,
    "low": 157.89,
    "close": null,
    "volume": 12034764
  },
  {
    "date": "2025-07-09",
    "open": 158.1,
    "high": 155.95,
    "low": 157.52,
    "close": null,
    "volume": 18770894
  },
  {
    "date": "2025-07-10",
    "open": 157.76,
    "high": 157.04,
    "low": 158.49,
    "close": null,
    "volume": 7201748
  },
  {
    "date": "2025-07-11",
    "open": 158.05,
    "high": 156.44,
    "low": 157.05,
    "close": null,
    "volume": 8053808
  },
  {
    "date": "2025-07-14",
    "open": 155.58,
    "high": 152.86,
    "low": 153.76,
    "close": null,
    "volume": 11491688
  },
  {
    "date": "2025-07-15",
    "open": 153.56,
    "high": 151.9,
    "low": 152.68,
    "close": null,
    "volume": 9142615
  },
  {
    "date": "2025-07-16",
    "open": 152.74,
    "high": 152.27,
    "low": 153.73,
    "close": null,
    "volume": 8478997
  },
  {
    "date": "2025-07-17",
    "open": 154.11,
    "high": 153.875,
    "low": 155.62,
    "close": null,
    "volume": 8319996
  },
  {
    "date": "2025-07-18",
    "open": 153.78,
    "high": 153.63,
    "low": 155.1,
    "close": null,
    "volume": 7337252
  },
  {
    "date": "2025-07-21",
    "open": 155.07,
    "high": 154.89,
    "low": 155.03,
    "close": null,
    "volume": 6328370
  },
  {
    "date": "2025-07-22",
    "open": 154.92,
    "high": 154.9,
    "low": 158.32,
    "close": null,
    "volume": 8186970
  },
  {
    "date": "2025-07-23",
    "open": 158.22,
    "high": 157.68,
    "low": 158.28,
    "close": null,
    "volume": 4804795
  },
  {
    "date": "2025-07-24",
    "open": 158.87,
    "high": 158.05,
    "low": 158.81,
    "close": null,
    "volume": 7027392
  },
  {
    "date": "2025-07-25",
    "open": 157.34,
    "high": 157.02,
    "low": 158.3,
    "close": null,
    "volume": 5800248
  },
  {
    "date": "2025-07-28",
    "open": 157.625,
    "high": 156.23,
    "low": 157.11,
    "close": null,
    "volume": 7885026
  },
  {
    "date": "2025-07-29",
    "open": 157.925,
    "high": 154.84,
    "low": 156.61,
    "close": null,
    "volume": 11466058
  },
  {
    "date": "2025-07-30",
    "open": 156.82,
    "high": 152.05,
    "low": 152.88,
    "close": null,
    "volume": 8162888
  },
  {
    "date": "2025-07-31",
    "open": 151.8,
    "high": 149.91,
    "low": 150.47,
    "close": null,
    "volume": 11845443
  },
  {
    "date": "2025-08-01",
    "open": 151.775,
    "high": 150.52,
    "low": 150.65,
    "close": null,
    "volume": 8594220
  },
  {
    "date": "2025-08-04",
    "open": 150.25,
    "high": 150.02,
    "low": 150.76,
    "close": null,
    "volume": 7679361
  },
  {
    "date": "2025-08-05",
    "open": 150.71,
    "high": 150.32,
    "low": 150.51,
    "close": null,
    "volume": 6670065
  },
  {
    "date": "2025-08-06",
    "open": 150.86,
    "high": 150.21,
    "low": 152.86,
    "close": null,
    "volume": 7376213
  },
  {
    "date": "2025-08-07",
    "open": 152.995,
    "high": 152.7,
    "low": 153.49,
    "close": null,
    "volume": 6719044
  },
  {
    "date": "2025-08-08",
    "open": 152.77,
    "high": 152.57,
    "low": 153.51,
    "close": null,
    "volume": 5811281
  },
  {
    "date": "2025-08-11",
    "open": 153.54,
    "high": 153.31,
    "low": 154.98,
    "close": null,
    "volume": 7331707
  },
  {
    "date": "2025-08-12",
    "open": 155.06,
    "high": 154.31,
    "low": 155.09,
    "close": null,
    "volume": 6938336
  },
  {
    "date": "2025-08-13",
    "open": 155.205,
    "high": 154.95,
    "low": 155.41,
    "close": null,
    "volume": 5812356
  },
  {
    "date": "2025-08-14",
    "open": 154.64,
    "high": 153.27,
    "low": 153.74,
    "close": null,
    "volume": 6343715
  },
  {
    "date": "2025-08-15",
    "open": 154.47,
    "high": 154.21,
    "low": 154.36,
    "close": null,
    "volume": 7121700
  },
  {
    "date": "2025-08-18",
    "open": 154.42,
    "high": 154.17,
    "low": 155.72,
    "close": null,
    "volume": 8274726
  },
  {
    "date": "2025-08-19",
    "open": 155.725,
    "high": 155.67,
    "low": 158.4,
    "close": null,
    "volume": 7868129
  },
  {
    "date": "2025-08-20",
    "open": 158.58,
    "high": 158.41,
    "low": 159.51,
    "close": null,
    "volume": 7840355
  },
  {
    "date": "2025-08-21",
    "open": 157.93,
    "high": 157.175,
    "low": 158.73,
    "close": null,
    "volume": 6417695
  },
  {
    "date": "2025-08-22",
    "open": 159.38,
    "high": 158.31,
    "low": 158.67,
    "close": null,
    "volume": 5797325
  },
  {
    "date": "2025-08-25",
    "open": 158.39,
    "high": 155.89,
    "low": 156.15,
    "close": null,
    "volume": 4692505
  },
  {
    "date": "2025-08-26",
    "open": 155.92,
    "high": 155.34,
    "low": 155.97,
    "close": null,
    "volume": 6337977
  },
  {
    "date": "2025-08-27",
    "open": 156.15,
    "high": 155.79,
    "low": 156.96,
    "close": null,
    "volume": 4551219
  },
  {
    "date": "2025-08-28",
    "open": 157,
    "high": 155.03,
    "low": 155.65,
    "close": null,
    "volume": 5857727
  },
  {
    "date": "2025-08-29",
    "open": 156.09,
    "high": 155.6501,
    "low": 157.04,
    "close": null,
    "volume": 5318179
  },
  {
    "date": "2025-09-02",
    "open": 157.36,
    "high": 156.98,
    "low": 157.99,
    "close": null,
    "volume": 6432837
  },
  {
    "date": "2025-09-03",
    "open": 157.65,
    "high": 156.495,
    "low": 158.17,
    "close": null,
    "volume": 6592451
  },
  {
    "date": "2025-09-04",
    "open": 158.52,
    "high": 157.81,
    "low": 159.19,
    "close": null,
    "volume": 6935245
  },
  {
    "date": "2025-09-05",
    "open": 158.55,
    "high": 158.41,
    "low": 160.02,
    "close": null,
    "volume": 6436150
  },
  {
    "date": "2025-09-08",
    "open": 159.61,
    "high": 158.25,
    "low": 159.01,
    "close": null,
    "volume": 7178356
  },
  {
    "date": "2025-09-09",
    "open": 158.61,
    "high": 158.195,
    "low": 159.46,
    "close": null,
    "volume": 4984936
  },
  {
    "date": "2025-09-10",
    "open": 158.595,
    "high": 155.89,
    "low": 157.35,
    "close": null,
    "volume": 6205463
  },
  {
    "date": "2025-09-11",
    "open": 157.72,
    "high": 157.39,
    "low": 158.63,
    "close": null,
    "volume": 5819875
  },
  {
    "date": "2025-09-12",
    "open": 157.93,
    "high": 157.78,
    "low": 157.9,
    "close": null,
    "volume": 5957021
  },
  {
    "date": "2025-09-15",
    "open": 157.88,
    "high": 156.2,
    "low": 156.83,
    "close": null,
    "volume": 5994966
  },
  {
    "date": "2025-09-16",
    "open": 157.135,
    "high": 156.89,
    "low": 158.05,
    "close": null,
    "volume": 6559608
  },
  {
    "date": "2025-09-17",
    "open": 158.425,
    "high": 158.425,
    "low": 160.33,
    "close": null,
    "volume": 6764169
  },
  {
    "date": "2025-09-18",
    "open": 158.15,
    "high": 157.16,
    "low": 157.32,
    "close": null,
    "volume": 7651487
  },
  {
    "date": "2025-09-19",
    "open": 157.61,
    "high": 155.97,
    "low": 156.04,
    "close": null,
    "volume": 17224774
  },
  {
    "date": "2025-09-22",
    "open": 156.08,
    "high": 153.05,
    "low": 153.07,
    "close": null,
    "volume": 8712910
  },
  {
    "date": "2025-09-23",
    "open": 153.195,
    "high": 150.97,
    "low": 152.5,
    "close": null,
    "volume": 8853418
  },
  {
    "date": "2025-09-24",
    "open": 152.05,
    "high": 151.79,
    "low": 152.42,
    "close": null,
    "volume": 6483264
  },
  {
    "date": "2025-09-25",
    "open": 153.23,
    "high": 151.78,
    "low": 152.15,
    "close": null,
    "volume": 7511415
  },
  {
    "date": "2025-09-26",
    "open": 152.23,
    "high": 151.53,
    "low": 152.5,
    "close": null,
    "volume": 5721092
  },
  {
    "date": "2025-09-29",
    "open": 152.42,
    "high": 151.7852,
    "low": 153.53,
    "close": null,
    "volume": 8139711
  },
  {
    "date": "2025-09-30",
    "open": 153.46,
    "high": 152.84,
    "low": 153.65,
    "close": null,
    "volume": 7762609
  },
  {
    "date": "2025-10-01",
    "open": 153.695,
    "high": 151.41,
    "low": 153.18,
    "close": null,
    "volume": 7566014
  },
  {
    "date": "2025-10-02",
    "open": 152.73,
    "high": 151.625,
    "low": 152.05,
    "close": null,
    "volume": 6892089
  },
  {
    "date": "2025-10-03",
    "open": 152,
    "high": 152,
    "low": 152.27,
    "close": null,
    "volume": 5212584
  },
  {
    "date": "2025-10-06",
    "open": 151.5,
    "high": 150.4,
    "low": 150.41,
    "close": null,
    "volume": 6736960
  },
  {
    "date": "2025-10-07",
    "open": 150.76,
    "high": 150.05,
    "low": 152.54,
    "close": null,
    "volume": 6844361
  },
  {
    "date": "2025-10-08",
    "open": 152.79,
    "high": 150.63,
    "low": 150.69,
    "close": null,
    "volume": 5254728
  },
  {
    "date": "2025-10-09",
    "open": 150.71,
    "high": 149.58,
    "low": 150.58,
    "close": null,
    "volume": 6134461
  },
  {
    "date": "2025-10-10",
    "open": 150.935,
    "high": 149.45,
    "low": 149.69,
    "close": null,
    "volume": 7374046
  },
  {
    "date": "2025-10-13",
    "open": 149,
    "high": 146.965,
    "low": 147.49,
    "close": null,
    "volume": 7511103
  },
  {
    "date": "2025-10-14",
    "open": 147.57,
    "high": 147.0802,
    "low": 149.16,
    "close": null,
    "volume": 8585346
  },
  {
    "date": "2025-10-15",
    "open": 148.525,
    "high": 147.27,
    "low": 147.42,
    "close": null,
    "volume": 10003073
  },
  {
    "date": "2025-10-16",
    "open": 147.99,
    "high": 147.92,
    "low": 149.6,
    "close": null,
    "volume": 8809673
  },
  {
    "date": "2025-10-17",
    "open": 150.57,
    "high": 150.43,
    "low": 151.4,
    "close": null,
    "volume": 8612894
  },
  {
    "date": "2025-10-20",
    "open": 151.53,
    "high": 151.29815,
    "low": 151.96,
    "close": null,
    "volume": 5601287
  },
  {
    "date": "2025-10-21",
    "open": 151.96,
    "high": 150.87,
    "low": 151.62,
    "close": null,
    "volume": 6013379
  },
  {
    "date": "2025-10-22",
    "open": 151.3,
    "high": 150.785,
    "low": 152.2,
    "close": null,
    "volume": 6394378
  },
  {
    "date": "2025-10-23",
    "open": 152.61,
    "high": 150.58,
    "low": 152.21,
    "close": null,
    "volume": 8205353
  },
  {
    "date": "2025-10-24",
    "open": 156.4,
    "high": 151.53,
    "low": 152.49,
    "close": null,
    "volume": 11968491
  },
  {
    "date": "2025-10-27",
    "open": 151.61,
    "high": 150.13,
    "low": 151.74,
    "close": null,
    "volume": 7775323
  },
  {
    "date": "2025-10-28",
    "open": 151.12,
    "high": 150.62,
    "low": 151.37,
    "close": null,
    "volume": 5819257
  },
  {
    "date": "2025-10-29",
    "open": 150.66,
    "high": 148.47,
    "low": 148.77,
    "close": null,
    "volume": 7405466
  },
  {
    "date": "2025-10-30",
    "open": 149.47,
    "high": 149.34,
    "low": 149.58,
    "close": null,
    "volume": 6760702
  },
  {
    "date": "2025-10-31",
    "open": 148.71,
    "high": 148.53,
    "low": 150.37,
    "close": null,
    "volume": 7930334
  },
  {
    "date": "2025-11-03",
    "open": 150.095,
    "high": 147.77,
    "low": 148.02,
    "close": null,
    "volume": 8946383
  },
  {
    "date": "2025-11-04",
    "open": 148.595,
    "high": 146.25,
    "low": 147.17,
    "close": null,
    "volume": 9295449
  },
  {
    "date": "2025-11-05",
    "open": 146.87,
    "high": 145.65,
    "low": 145.79,
    "close": null,
    "volume": 11199878
  },
  {
    "date": "2025-11-06",
    "open": 145.34,
    "high": 144.46,
    "low": 146.13,
    "close": null,
    "volume": 10024549
  },
  {
    "date": "2025-11-07",
    "open": 146.85,
    "high": 146,
    "low": 146.98,
    "close": null,
    "volume": 8500097
  },
  {
    "date": "2025-11-10",
    "open": 146.38,
    "high": 144.09,
    "low": 145.5,
    "close": null,
    "volume": 10208085
  },
  {
    "date": "2025-11-11",
    "open": 145.955,
    "high": 145.67,
    "low": 148.54,
    "close": null,
    "volume": 7332540
  },
  {
    "date": "2025-11-12",
    "open": 148.53,
    "high": 147.51,
    "low": 148.01,
    "close": null,
    "volume": 7851052
  },
  {
    "date": "2025-11-13",
    "open": 148.18,
    "high": 147.64,
    "low": 147.96,
    "close": null,
    "volume": 7566789
  },
  {
    "date": "2025-11-14",
    "open": 149.1,
    "high": 147.61,
    "low": 147.67,
    "close": null,
    "volume": 9151066
  },
  {
    "date": "2025-11-17",
    "open": 147.75,
    "high": 145.01,
    "low": 145.82,
    "close": null,
    "volume": 9902310
  },
  {
    "date": "2025-11-18",
    "open": 146.325,
    "high": 145.51,
    "low": 146.99,
    "close": null,
    "volume": 10735177
  },
  {
    "date": "2025-11-19",
    "open": 146.96,
    "high": 145.86,
    "low": 146.99,
    "close": null,
    "volume": 6367038
  },
  {
    "date": "2025-11-20",
    "open": 146.64,
    "high": 146.13,
    "low": 148.19,
    "close": null,
    "volume": 9021325
  },
  {
    "date": "2025-11-21",
    "open": 148.38,
    "high": 148.3032,
    "low": 150.92,
    "close": null,
    "volume": 12017986
  },
  {
    "date": "2025-11-24",
    "open": 150.1,
    "high": 146.54,
    "low": 146.98,
    "close": null,
    "volume": 13846906
  },
  {
    "date": "2025-11-25",
    "open": 147.32,
    "high": 147.22,
    "low": 148.49,
    "close": null,
    "volume": 10477661
  },
  {
    "date": "2025-11-26",
    "open": 147.92,
    "high": 147.605,
    "low": 148.25,
    "close": null,
    "volume": 9238450
  },
  {
    "date": "2025-11-28",
    "open": 147.8,
    "high": 147.18,
    "low": 148.16,
    "close": null,
    "volume": 4707161
  },
  {
    "date": "2025-12-01",
    "open": 148.36,
    "high": 147.35,
    "low": 147.44,
    "close": null,
    "volume": 8240689
  },
  {
    "date": "2025-12-02",
    "open": 145.29,
    "high": 142.51,
    "low": 145.86,
    "close": null,
    "volume": 16376769
  },
  {
    "date": "2025-12-03",
    "open": 145.915,
    "high": 145.86,
    "low": 146.71,
    "close": null,
    "volume": 9125320
  },
  {
    "date": "2025-12-04",
    "open": 146.67,
    "high": 144.5,
    "low": 145.36,
    "close": null,
    "volume": 10479267
  },
  {
    "date": "2025-12-05",
    "open": 145.19,
    "high": 143.25,
    "low": 143.45,
    "close": null,
    "volume": 12791745
  },
  {
    "date": "2025-12-08",
    "open": 142.905,
    "high": 138.14,
    "low": 138.34,
    "close": null,
    "volume": 17507504
  },
  {
    "date": "2025-12-09",
    "open": 139.19,
    "high": 139,
    "low": 139.63,
    "close": null,
    "volume": 10375688
  },
  {
    "date": "2025-12-10",
    "open": 139.69,
    "high": 139.54,
    "low": 139.82,
    "close": null,
    "volume": 13650378
  },
  {
    "date": "2025-12-11",
    "open": 141,
    "high": 140.355,
    "low": 140.76,
    "close": null,
    "volume": 11797981
  },
  {
    "date": "2025-12-12",
    "open": 141,
    "high": 140.835,
    "low": 142.84,
    "close": null,
    "volume": 10268768
  },
  {
    "date": "2025-12-15",
    "open": 143.26,
    "high": 143.2,
    "low": 145.13,
    "close": null,
    "volume": 13877674
  },
  {
    "date": "2025-12-16",
    "open": 146.1,
    "high": 144.65,
    "low": 145.21,
    "close": null,
    "volume": 10251720
  },
  {
    "date": "2025-12-17",
    "open": 146.69,
    "high": 146.45,
    "low": 147.81,
    "close": null,
    "volume": 9833261
  },
  {
    "date": "2025-12-18",
    "open": 146.62,
    "high": 145.35,
    "low": 145.52,
    "close": null,
    "volume": 12239860
  },
  {
    "date": "2025-12-19",
    "open": 145.505,
    "high": 143.94,
    "low": 144.46,
    "close": null,
    "volume": 19345622
  },
  {
    "date": "2025-12-22",
    "open": 143.705,
    "high": 142.42,
    "low": 142.69,
    "close": null,
    "volume": 11731360
  },
  {
    "date": "2025-12-23",
    "open": 142.08,
    "high": 142.08,
    "low": 143.18,
    "close": null,
    "volume": 9541563
  },
  {
    "date": "2025-12-24",
    "open": 142.9,
    "high": 142.83,
    "low": 144.49,
    "close": null,
    "volume": 3259209
  },
  {
    "date": "2025-12-26",
    "open": 144.31,
    "high": 144.31,
    "low": 144.74,
    "close": null,
    "volume": 4711505
  },
  {
    "date": "2025-12-29",
    "open": 144.87,
    "high": 143.945,
    "low": 144.57,
    "close": null,
    "volume": 7662127
  },
  {
    "date": "2025-12-30",
    "open": 144.29,
    "high": 143.57,
    "low": 144.05,
    "close": null,
    "volume": 6006432
  },
  {
    "date": "2025-12-31",
    "open": 144,
    "high": 143.23,
    "low": 143.31,
    "close": null,
    "volume": 5293220
  },
  {
    "date": "2026-01-02",
    "open": 143.11,
    "high": 141.24,
    "low": 141.79,
    "close": null,
    "volume": 8946091
  },
  {
    "date": "2026-01-05",
    "open": 141.1,
    "high": 139.6001,
    "low": 140.37,
    "close": null,
    "volume": 12297334
  },
  {
    "date": "2026-01-06",
    "open": 140.41,
    "high": 139.51,
    "low": 139.91,
    "close": null,
    "volume": 10421756
  },
  {
    "date": "2026-01-07",
    "open": 139.8,
    "high": 137.62,
    "low": 138.04,
    "close": null,
    "volume": 14369142
  },
  {
    "date": "2026-01-08",
    "open": 137.89,
    "high": 137.82,
    "low": 141.53,
    "close": null,
    "volume": 9297080
  },
  {
    "date": "2026-01-09",
    "open": 141.7,
    "high": 140.83,
    "low": 141.87,
    "close": null,
    "volume": 9528476
  },
  {
    "date": "2026-01-12",
    "open": 142.65,
    "high": 141.7124,
    "low": 143.46,
    "close": null,
    "volume": 12812014
  },
  {
    "date": "2026-01-13",
    "open": 144,
    "high": 142.97,
    "low": 144.24,
    "close": null,
    "volume": 15549150
  },
  {
    "date": "2026-01-14",
    "open": 144.68,
    "high": 144.37,
    "low": 146.35,
    "close": null,
    "volume": 13474983
  },
  {
    "date": "2026-01-15",
    "open": 145.68,
    "high": 144.35,
    "low": 144.63,
    "close": null,
    "volume": 10102757
  },
  {
    "date": "2026-01-16",
    "open": 143.76,
    "high": 143.655,
    "low": 144.53,
    "close": null,
    "volume": 11729334
  },
  {
    "date": "2026-01-20",
    "open": 144.42,
    "high": 144.12,
    "low": 147,
    "close": null,
    "volume": 12901430
  },
  {
    "date": "2026-01-21",
    "open": 147.06,
    "high": 144.97,
    "low": 146.06,
    "close": null,
    "volume": 14126814
  },
  {
    "date": "2026-01-22",
    "open": 148.08,
    "high": 147.5,
    "low": 149.93,
    "close": null,
    "volume": 18501854
  },
  {
    "date": "2026-01-23",
    "open": 150.84,
    "high": 149.8,
    "low": 150.15,
    "close": null,
    "volume": 14562626
  },
  {
    "date": "2026-01-26",
    "open": 150.115,
    "high": 148.52,
    "low": 149.49,
    "close": null,
    "volume": 12655663
  },
  {
    "date": "2026-01-27",
    "open": 148.07,
    "high": 147.925,
    "low": 148.34,
    "close": null,
    "volume": 9546000
  },
  {
    "date": "2026-01-28",
    "open": 148,
    "high": 146.79,
    "low": 147.34,
    "close": null,
    "volume": 7465812
  },
  {
    "date": "2026-01-29",
    "open": 147.29,
    "high": 147.113,
    "low": 149.9,
    "close": null,
    "volume": 11035563
  },
  {
    "date": "2026-01-30",
    "open": 150.43,
    "high": 149.145,
    "low": 151.77,
    "close": null,
    "volume": 12651426
  },
  {
    "date": "2026-02-02",
    "open": 152.42,
    "high": 151.25,
    "low": 153.19,
    "close": null,
    "volume": 10554872
  },
  {
    "date": "2026-02-03",
    "open": 152.59,
    "high": 152.2,
    "low": 155.32,
    "close": null,
    "volume": 12424740
  },
  {
    "date": "2026-02-04",
    "open": 156.125,
    "high": 155.76,
    "low": 156.87,
    "close": null,
    "volume": 12178463
  },
  {
    "date": "2026-02-05",
    "open": 158.84,
    "high": 156.12,
    "low": 158.61,
    "close": null,
    "volume": 13077657
  },
  {
    "date": "2026-02-06",
    "open": 158.24,
    "high": 158.01,
    "low": 159.17,
    "close": null,
    "volume": 10441737
  },
  {
    "date": "2026-02-09",
    "open": 158.76,
    "high": 156.02,
    "low": 157.33,
    "close": null,
    "volume": 11439942
  },
  {
    "date": "2026-02-10",
    "open": 157.53,
    "high": 156.72,
    "low": 159.08,
    "close": null,
    "volume": 9910099
  },
  {
    "date": "2026-02-11",
    "open": 158.64,
    "high": 158.19,
    "low": 160,
    "close": null,
    "volume": 10217309
  },
  {
    "date": "2026-02-12",
    "open": 160.02,
    "high": 159.65,
    "low": 161.21,
    "close": null,
    "volume": 13512862
  },
  {
    "date": "2026-02-13",
    "open": 161.74,
    "high": 159.705,
    "low": 160.07,
    "close": null,
    "volume": 13999208
  },
  {
    "date": "2026-02-17",
    "open": 159.95,
    "high": 158.88,
    "low": 159.55,
    "close": null,
    "volume": 13319135
  },
  {
    "date": "2026-02-18",
    "open": 158.98,
    "high": 155.77,
    "low": 156.86,
    "close": null,
    "volume": 14434308
  },
  {
    "date": "2026-02-19",
    "open": 156.825,
    "high": 156.825,
    "low": 158.56,
    "close": null,
    "volume": 10724558
  },
  {
    "date": "2026-02-20",
    "open": 159.125,
    "high": 158.16,
    "low": 160.78,
    "close": null,
    "volume": 11508133
  },
  {
    "date": "2026-02-23",
    "open": 160.32,
    "high": 160.3,
    "low": 165.17,
    "close": null,
    "volume": 14772449
  },
  {
    "date": "2026-02-24",
    "open": 164.9,
    "high": 163.94,
    "low": 165.28,
    "close": null,
    "volume": 9709847
  },
  {
    "date": "2026-02-25",
    "open": 164.37,
    "high": 162.1,
    "low": 163.39,
    "close": null,
    "volume": 7878500
  },
  {
    "date": "2026-02-26",
    "open": 164.22,
    "high": 162.86,
    "low": 163.75,
    "close": null,
    "volume": 7018299
  },
  {
    "date": "2026-02-27",
    "open": 164.04,
    "high": 163.685,
    "low": 167.2,
    "close": null,
    "volume": 14857372
  },
  {
    "date": "2026-03-02",
    "open": 165.29,
    "high": 163.45,
    "low": 163.51,
    "close": null,
    "volume": 9095500
  },
  {
    "date": "2026-03-03",
    "open": 162.19,
    "high": 158.62,
    "low": 159.72,
    "close": null,
    "volume": 10161000
  },
  {
    "date": "2026-03-04",
    "open": 159.44,
    "high": 157.31,
    "low": 158.3,
    "close": null,
    "volume": 8752716
  },
  {
    "date": "2026-03-05",
    "open": 156.935,
    "high": 153.77,
    "low": 153.99,
    "close": null,
    "volume": 10060314
  },
  {
    "date": "2026-03-06",
    "open": 153.66,
    "high": 151.89,
    "low": 153.63,
    "close": null,
    "volume": 8187905
  },
  {
    "date": "2026-03-09",
    "open": 153.15,
    "high": 152.9,
    "low": 155.22,
    "close": null,
    "volume": 12494929
  },
  {
    "date": "2026-03-10",
    "open": 155.49,
    "high": 153.6,
    "low": 156.01,
    "close": null,
    "volume": 7756771
  },
  {
    "date": "2026-03-11",
    "open": 155.24,
    "high": 151.43,
    "low": 153.32,
    "close": null,
    "volume": 8857194
  },
  {
    "date": "2026-03-12",
    "open": 152.21,
    "high": 150.33,
    "low": 150.5,
    "close": null,
    "volume": 8489278
  },
  {
    "date": "2026-03-13",
    "open": 151.37,
    "high": 150.18,
    "low": 150.65,
    "close": null,
    "volume": 7298896
  }
]